deg_pathway_enrichment_tool/__init__.py
deg_pathway_enrichment_tool/cli.py
deg_pathway_enrichment_tool/core.py
deg_pathway_enrichment_tool-1.0.0.dist-info/licenses/LICENSE
deg_pathway_enrichment_tool-1.0.0.dist-info/METADATA
deg_pathway_enrichment_tool-1.0.0.dist-info/WHEEL
deg_pathway_enrichment_tool-1.0.0.dist-info/entry_points.txt
deg_pathway_enrichment_tool-1.0.0.dist-info/top_level.txt
deg_pathway_enrichment_tool-1.0.0.dist-info/RECORD
