Metadata-Version: 2.4
Name: deg-pathway-enrichment-tool
Version: 1.0.0
Summary: A comprehensive tool for differential gene expression pathway enrichment analysis
Author-email: DEG Analysis Team <contact@example.com>
License: MIT
Project-URL: Homepage, https://github.com/yourusername/deg-pathway-enrichment-tool
Project-URL: Repository, https://github.com/yourusername/deg-pathway-enrichment-tool
Project-URL: Issues, https://github.com/yourusername/deg-pathway-enrichment-tool/issues
Classifier: Development Status :: 4 - Beta
Classifier: Intended Audience :: Science/Research
Classifier: License :: OSI Approved :: MIT License
Classifier: Programming Language :: Python :: 3
Classifier: Programming Language :: Python :: 3.8
Classifier: Programming Language :: Python :: 3.9
Classifier: Programming Language :: Python :: 3.10
Classifier: Programming Language :: Python :: 3.11
Classifier: Topic :: Scientific/Engineering :: Bio-Informatics
Requires-Python: >=3.8
License-File: LICENSE
Requires-Dist: pandas>=2.0.0
Requires-Dist: numpy>=1.24.0
Requires-Dist: matplotlib>=3.7.0
Requires-Dist: seaborn>=0.12.0
Requires-Dist: plotly>=5.15.0
Requires-Dist: gseapy>=1.0.4
Requires-Dist: scipy>=1.10.0
Requires-Dist: requests>=2.31.0
Provides-Extra: dev
Requires-Dist: pytest>=7.0.0; extra == "dev"
Requires-Dist: black>=23.0.0; extra == "dev"
Requires-Dist: flake8>=6.0.0; extra == "dev"
Dynamic: license-file
